dhisana/__init__.py
dhisana/cli/__init__.py
dhisana/cli/cli.py
dhisana/cli/datasets.py
dhisana/cli/models.py
dhisana/cli/predictions.py
dhisana/utils/__init__.py
dhisana/utils/agent_tools.py
dhisana/utils/tools_json.py
dhisana-0.1.0.dist-info/METADATA
dhisana-0.1.0.dist-info/WHEEL
dhisana-0.1.0.dist-info/entry_points.txt
dhisana-0.1.0.dist-info/top_level.txt
dhisana-0.1.0.dist-info/RECORD
